benderthon/__init__.py
benderthon/caffe_freeze.py
benderthon/cmdline.py
benderthon/tf_freeze.py
benderthon/util.py
benderthon-0.3.0.dist-info/DESCRIPTION.rst
benderthon-0.3.0.dist-info/LICENSE.txt
benderthon-0.3.0.dist-info/METADATA
benderthon-0.3.0.dist-info/RECORD
benderthon-0.3.0.dist-info/WHEEL
benderthon-0.3.0.dist-info/entry_points.txt
benderthon-0.3.0.dist-info/metadata.json
benderthon-0.3.0.dist-info/top_level.txt
