Metadata-Version: 2.0
Name: benderthon
Version: 0.3.0
Summary: Set of utilities to work easier with Bender.
Home-page: https://github.com/xmartlabs/benderthon
Author: Santiago Castro
Author-email: santiago@xmartlabs.com
License: Apache 2.0
Keywords: Bender,machine learning,artificial intelligence,freeze,model,utility,utilities,TensorFlow
Platform: UNKNOWN
Classifier: Development Status :: 3 - Alpha
Classifier: Environment :: Console
Classifier: Intended Audience :: Developers
Classifier: Intended Audience :: Science/Research
Classifier: License :: OSI Approved :: Apache Software License
Classifier: Operating System :: OS Independent
Classifier: Programming Language :: Python
Classifier: Programming Language :: Python :: 2
Classifier: Programming Language :: Python :: 2.7
Classifier: Programming Language :: Python :: 3
Classifier: Programming Language :: Python :: 3.3
Classifier: Programming Language :: Python :: 3.4
Classifier: Programming Language :: Python :: 3.5
Classifier: Programming Language :: Python :: 3.6
Classifier: Topic :: Scientific/Engineering
Classifier: Topic :: Scientific/Engineering :: Artificial Intelligence
